stellar_domains_sdk/__init__.py
stellar_domains_sdk/client.py
stellar_domains_sdk/exceptions.py
stellar_domains_sdk/models.py
stellar_domains_sdk-0.1.0.dist-info/METADATA
stellar_domains_sdk-0.1.0.dist-info/WHEEL
stellar_domains_sdk-0.1.0.dist-info/top_level.txt
stellar_domains_sdk-0.1.0.dist-info/RECORD
