Metadata-Version: 2.1
Name: stellar_domains_sdk
Version: 0.1.0
Summary: A Python SDK for interacting with Soroban Domains on the Stellar network
Author-email: Matej Plavevski <matej.plavevski+pypi@gmail.com>
License: MIT
Project-URL: Homepage, https://github.com/matejmecka/stellar-python-domains-sdk
Project-URL: Repository, https://github.com/matejmecka/stellar-python-domains-sdk.git
Project-URL: Documentation, https://github.com/matejmecka/stellar-python-domains-sdk#readme
Keywords: stellar,blockchain,domains,soroban,sdk
Classifier: Programming Language :: Python :: 3
Classifier: Programming Language :: Python :: 3.7
Classifier: Programming Language :: Python :: 3.8
Classifier: Programming Language :: Python :: 3.9
Classifier: Programming Language :: Python :: 3.10
Classifier: License :: OSI Approved :: MIT License
Classifier: Operating System :: OS Independent
Requires-Python: >=3.7
Requires-Dist: stellar-sdk>=8.0.0
Requires-Dist: safe-pysha3>=1.0.4
Requires-Dist: dataclasses; python_version < "3.7"
